<?xml version="1.0" encoding="UTF-8"?>
<enderio:recipes xmlns:enderio="http://enderio.com/recipes" xmlns:xsi="http://www.w3.org/2001/XMLSchema-instance" xsi:schemaLocation="http://enderio.com/recipes recipes.xsd ">
	<capacitor key="enderio:item_dark_steel_sword/absorption" base="1" scaler="idx(1)0:0.5:0.75:0.85:1.0" />
	<capacitor key="enderio:item_dark_steel_chestplate/absorption" base="1" scaler="idx(1)0:0.5:0.75:0.85:1.0" />
	<capacitor key="enderio:item_dark_steel_shield/absorption" base="1" scaler="idx(1)0:0.5:0.75:0.85:1.0" />
	<capacitor key="enderio:item_dark_steel_axe/absorption" base="1" scaler="idx(1)0:0.5:0.75:0.85:1.0" />
	<capacitor key="enderio:item_dark_steel_crook/absorption" base="1" scaler="idx(1)0:0.5:0.75:0.85:1.0" />
	<capacitor key="enderio:item_dark_steel_bow/absorption" base="1" scaler="idx(1)0:0.5:0.75:0.85:1.0" />
	<capacitor key="enderio:item_dark_steel_pickaxe/absorption" base="1" scaler="idx(1)0:0.5:0.75:0.85:1.0" />
	<capacitor key="enderio:item_dark_steel_shears/absorption" base="1" scaler="idx(1)0:0.5:0.75:0.85:1.0" />
	<capacitor key="enderio:item_dark_steel_treetap/absorption" base="1" scaler="idx(1)0:0.5:0.75:0.85:1.0" />
	<capacitor key="enderio:item_dark_steel_hand/absorption" base="1" scaler="idx(1)0:0.5:0.75:0.85:1.0" />
</enderio:recipes>